Workbook

Sheet Sources
A1: Source figures, USD millions
A2: Tied to the 10-K statement lines named in the PDF sources. Base years are shaded. Net debt and the ratios are formulas.
A4: Line | B4: NVIDIA FY21 | C4: NVIDIA FY22 | D4: NVIDIA FY23 | E4: NVIDIA FY24 | F4: NVIDIA FY25 | G4: NVIDIA FY26 | H4: AMD FY20 | I4: AMD FY21 | J4: AMD FY22 | K4: AMD FY23 | L4: AMD FY24 | M4: AMD FY25 | N4: Intel FY20 | O4: Intel FY21 | P4: Intel FY22 | Q4: Intel FY23 | R4: Intel FY24 | S4: Intel FY25
A5: Revenue | B5: 16675 | C5: 26914 | D5: 26974 | E5: 60922 | F5: 130497 | G5: 215938 | H5: 9763 | I5: 16434 | J5: 23601 | K5: 22680 | L5: 25785 | M5: 34639 | N5: 77867 | O5: 79024 | P5: 63054 | Q5: 54228 | R5: 53101 | S5: 52853
A6: Operating income | B6: 4532 | C6: 10041 | D6: 4224 | E6: 32972 | F6: 81453 | G6: 130387 | H6: 1369 | I6: 3648 | J6: 1264 | K6: 401 | L6: 1900 | M6: 3694 | N6: 23678 | O6: 19456 | P6: 2334 | Q6: 93 | R6: -11678 | S6: -2214
A7: Net income to the company | B7: 4332 | C7: 9752 | D7: 4368 | E7: 29760 | F7: 72880 | G7: 120067 | H7: 2490 | I7: 3162 | J7: 1320 | K7: 854 | L7: 1641 | M7: 4335 | N7: 20899 | O7: 19868 | P7: 8017 | Q7: 1675 | R7: -19233 | S7: 26
A8: Interest expense | B8: 184 | C8: 236 | D8: 262 | E8: 257 | F8: 247 | G8: 259 | H8: 47 | I8: 34 | J8: 88 | K8: 106 | L8: 92 | M8: 131 | N8: 629 | O8: 597 | P8: 496 | Q8: 878 | R8: 1034 | S8: 1091
A9: Interest income | B9: 57 | C9: 29 | D9: 267 | E9: 866 | F9: 1786 | G9: 2300 | H9: 8 | I9: 8 | J9: 65 | K9: 206 | L9: 182 | M9: 215 | N9: 272 | O9: 144 | P9: 589 | Q9: 1335 | R9: 1245 | S9: 1007
A10: Total assets | B10: 28791 | C10: 44187 | D10: 41182 | E10: 65728 | F10: 111601 | G10: 206803 | H10: 8962 | I10: 12419 | J10: 67580 | K10: 67885 | L10: 69226 | M10: 76926 | N10: 153091 | O10: 168406 | P10: 182103 | Q10: 191572 | R10: 196485 | S10: 211429
A11: Equity, including NCI where presented | B11: 16893 | C11: 26612 | D11: 22101 | E11: 42978 | F11: 79327 | G11: 157293 | H11: 5837 | I11: 7497 | J11: 54750 | K11: 55892 | L11: 57568 | M11: 62999 | N11: 81038 | O11: 95391 | P11: 103286 | Q11: 109965 | R11: 105032 | S11: 126360
A12: Cash | B12: 847 | C12: 1990 | D12: 3389 | E12: 7280 | F12: 8589 | G12: 10605 | H12: 1595 | I12: 2535 | J12: 4835 | K12: 3933 | L12: 3787 | M12: 5539 | N12: 5865 | O12: 4827 | P12: 11144 | Q12: 7079 | R12: 8249 | S12: 14265
A13: Marketable securities or short-term investments | B13: 10714 | C13: 19218 | D13: 9907 | E13: 18704 | F13: 34621 | G13: 51951 | H13: 695 | I13: 1073 | J13: 1020 | K13: 1840 | L13: 1345 | M13: 5013 | N13: 2292 | O13: 24426 | P13: 17194 | Q13: 17955 | R13: 13813 | S13: 23151
A14: Debt, including current portion | B14: 6963 | C14: 10946 | D14: 10953 | E14: 9709 | F14: 8463 | G14: 8468 | H14: 330 | I14: 313 | J14: 2467 | K14: 2468 | L14: 1721 | M14: 3222 | N14: 36401 | O14: 38101 | P14: 42051 | Q14: 49266 | R14: 50011 | S14: 46585
A15: Long-term operating lease liability | B15: 634 | C15: 741 | D15: 902 | E15: 1119 | F15: 1519 | G15: 2572 | H15: 201 | I15: 348 | J15: 396 | K15: 535 | L15: 491 | M15: 625 | N15: 0 | O15: 0 | P15: 0 | Q15: 0 | R15: 0 | S15: 0
A16: Operating cash flow | B16: 5822 | C16: 9108 | D16: 5641 | E16: 28090 | F16: 64089 | G16: 102718 | H16: 1071 | I16: 3521 | J16: 3565 | K16: 1667 | L16: 3041 | M16: 7709 | N16: 35864 | O16: 29456 | P16: 15433 | Q16: 11471 | R16: 8288 | S16: 9697
A17: Capital expenditures, cash spent | B17: 1128 | C17: 976 | D17: 1833 | E17: 1069 | F17: 3236 | G17: 6042 | H17: 294 | I17: 301 | J17: 450 | K17: 546 | L17: 636 | M17: 1012 | N17: 14259 | O17: 18733 | P17: 24844 | Q17: 25750 | R17: 23944 | S17: 14646
A18: Net debt = debt + lease - cash - liquid investments | B18: =B14+B15-B12-B13 -> 0 | C18: =C14+C15-C12-C13 -> 0 | D18: =D14+D15-D12-D13 -> 0 | E18: =E14+E15-E12-E13 -> 0 | F18: =F14+F15-F12-F13 -> 0 | G18: =G14+G15-G12-G13 -> 0 | H18: =H14+H15-H12-H13 -> 0 | I18: =I14+I15-I12-I13 -> 0 | ... S18: =S14+S15-S12-S13 -> 0
A19: After-tax net interest = (interest expense - interest income) x 0.79 | B19: =(B8-B9)*(1-0.21) -> 0 | C19: =(C8-C9)*(1-0.21) -> 0 | D19: =(D8-D9)*(1-0.21) -> 0 | E19: =(E8-E9)*(1-0.21) -> 0 | F19: =(F8-F9)*(1-0.21) -> 0 | G19: =(G8-G9)*(1-0.21) -> 0 | H19: =(H8-H9)*(1-0.21) -> 0 | I19: =(I8-I9)*(1-0.21) -> 0 | ... S19: =(S8-S9)*(1-0.21) -> 0
A20: NOPAT = net income + after-tax net interest | B20: =B7+B19 -> 0 | C20: =C7+C19 -> 0 | D20: =D7+D19 -> 0 | E20: =E7+E19 -> 0 | F20: =F7+F19 -> 0 | G20: =G7+G19 -> 0 | H20: =H7+H19 -> 0 | I20: =I7+I19 -> 0 | ... S20: =S7+S19 -> 0
A22: Intel FY2020 and FY2021 operating cash flow is the revised comparative in the later cash-flow statement (originally $35,384 and $29,991). Intel FY2020 trading assets of $15,738 are not in liquid investments. AMD FY2025 capex of $1,012 and operating cash flow of $7,709 include discontinued operations ($38 and $1,216). Intel capex is the investing-section additions, not the further additions classified in financing ($3,026 in 2025 and $1,178 in 2024). Current operating lease liabilities are inside accrued liabilities and are not in net debt.

Sheet DuPont
A1: NVIDIA vs AMD vs Intel: advanced DuPont
A2: Every ratio is a formula. YES tests the unrounded identity. Shaded columns are the base year and are not ratio years. n.m. is not used; average net debt is never near zero in this panel.
B3: NVIDIA | H3: AMD | N3: Intel
A4: RATIOS | B4: FY21 | C4: FY22 | D4: FY23 | E4: FY24 | F4: FY25 | G4: FY26 | H4: FY20 | I4: FY21 | J4: FY22 | K4: FY23 | L4: FY24 | M4: FY25 | N4: FY20 | O4: FY21 | P4: FY22 | Q4: FY23 | R4: FY24 | S4: FY25
A6: Traditional DuPont
A7: Net margin | C7: =Sources!C7/Sources!C5 -> 0 | D7: =Sources!D7/Sources!D5 -> 0 | E7: =Sources!E7/Sources!E5 -> 0 | F7: =Sources!F7/Sources!F5 -> 0 | G7: =Sources!G7/Sources!G5 -> 0 | I7: =Sources!I7/Sources!I5 -> 0 | J7: =Sources!J7/Sources!J5 -> 0 | K7: =Sources!K7/Sources!K5 -> 0 | L7: =Sources!L7/Sources!L5 -> 0 | M7: =Sources!M7/Sources!M5 -> 0 | O7: =Sources!O7/Sources!O5 -> 0 | P7: =Sources!P7/Sources!P5 -> 0 | Q7: =Sources!Q7/Sources!Q5 -> 0 | R7: =Sources!R7/Sources!R5 -> 0 | S7: =Sources!S7/Sources!S5 -> 0
A8: x Asset turnover (sales / avg total assets) | C8: =Sources!C5/(((Sources!B10)+(Sources!C10))/2) -> 0 | D8: =Sources!D5/(((Sources!C10)+(Sources!D10))/2) -> 0 | E8: =Sources!E5/(((Sources!D10)+(Sources!E10))/2) -> 0 | F8: =Sources!F5/(((Sources!E10)+(Sources!F10))/2) -> 0 | G8: =Sources!G5/(((Sources!F10)+(Sources!G10))/2) -> 0 | I8: =Sources!I5/(((Sources!H10)+(Sources!I10))/2) -> 0 | J8: =Sources!J5/(((Sources!I10)+(Sources!J10))/2) -> 0 | K8: =Sources!K5/(((Sources!J10)+(Sources!K10))/2) -> 0 | L8: =Sources!L5/(((Sources!K10)+(Sources!L10))/2) -> 0 | M8: =Sources!M5/(((Sources!L10)+(Sources!M10))/2) -> 0 | O8: =Sources!O5/(((Sources!N10)+(Sources!O10))/2) -> 0 | P8: =Sources!P5/(((Sources!O10)+(Sources!P10))/2) -> 0 | Q8: =Sources!Q5/(((Sources!P10)+(Sources!Q10))/2) -> 0 | R8: =Sources!R5/(((Sources!Q10)+(Sources!R10))/2) -> 0 | S8: =Sources!S5/(((Sources!R10)+(Sources!S10))/2) -> 0
A9: x Leverage (avg assets / avg equity) | C9: =(((Sources!B10)+(Sources!C10))/2)/(((Sources!B11)+(Sources!C11))/2) -> 0 | D9: =(((Sources!C10)+(Sources!D10))/2)/(((Sources!C11)+(Sources!D11))/2) -> 0 | E9: =(((Sources!D10)+(Sources!E10))/2)/(((Sources!D11)+(Sources!E11))/2) -> 0 | F9: =(((Sources!E10)+(Sources!F10))/2)/(((Sources!E11)+(Sources!F11))/2) -> 0 | G9: =(((Sources!F10)+(Sources!G10))/2)/(((Sources!F11)+(Sources!G11))/2) -> 0 | I9: =(((Sources!H10)+(Sources!I10))/2)/(((Sources!H11)+(Sources!I11))/2) -> 0 | J9: =(((Sources!I10)+(Sources!J10))/2)/(((Sources!I11)+(Sources!J11))/2) -> 0 | K9: =(((Sources!J10)+(Sources!K10))/2)/(((Sources!J11)+(Sources!K11))/2) -> 0 | L9: =(((Sources!K10)+(Sources!L10))/2)/(((Sources!K11)+(Sources!L11))/2) -> 0 | M9: =(((Sources!L10)+(Sources!M10))/2)/(((Sources!L11)+(Sources!M11))/2) -> 0 | O9: =(((Sources!N10)+(Sources!O10))/2)/(((Sources!N11)+(Sources!O11))/2) -> 0 | P9: =(((Sources!O10)+(Sources!P10))/2)/(((Sources!O11)+(Sources!P11))/2) -> 0 | Q9: =(((Sources!P10)+(Sources!Q10))/2)/(((Sources!P11)+(Sources!Q11))/2) -> 0 | R9: =(((Sources!Q10)+(Sources!R10))/2)/(((Sources!Q11)+(Sources!R11))/2) -> 0 | S9: =(((Sources!R10)+(Sources!S10))/2)/(((Sources!R11)+(Sources!S11))/2) -> 0
A10: ROE (NI / avg equity) | C10: =Sources!C7/(((Sources!B11)+(Sources!C11))/2) -> 0 | D10: =Sources!D7/(((Sources!C11)+(Sources!D11))/2) -> 0 | E10: =Sources!E7/(((Sources!D11)+(Sources!E11))/2) -> 0 | F10: =Sources!F7/(((Sources!E11)+(Sources!F11))/2) -> 0 | G10: =Sources!G7/(((Sources!F11)+(Sources!G11))/2) -> 0 | I10: =Sources!I7/(((Sources!H11)+(Sources!I11))/2) -> 0 | J10: =Sources!J7/(((Sources!I11)+(Sources!J11))/2) -> 0 | K10: =Sources!K7/(((Sources!J11)+(Sources!K11))/2) -> 0 | L10: =Sources!L7/(((Sources!K11)+(Sources!L11))/2) -> 0 | M10: =Sources!M7/(((Sources!L11)+(Sources!M11))/2) -> 0 | O10: =Sources!O7/(((Sources!N11)+(Sources!O11))/2) -> 0 | P10: =Sources!P7/(((Sources!O11)+(Sources!P11))/2) -> 0 | Q10: =Sources!Q7/(((Sources!P11)+(Sources!Q11))/2) -> 0 | R10: =Sources!R7/(((Sources!Q11)+(Sources!R11))/2) -> 0 | S10: =Sources!S7/(((Sources!R11)+(Sources!S11))/2) -> 0
A11: Check: ROE = margin x turnover x leverage | C11: =IF(ABS(C7*C8*C9-C10)<0.0000005,"YES","NO") -> 0 | D11: =IF(ABS(D7*D8*D9-D10)<0.0000005,"YES","NO") -> 0 | E11: =IF(ABS(E7*E8*E9-E10)<0.0000005,"YES","NO") -> 0 | F11: =IF(ABS(F7*F8*F9-F10)<0.0000005,"YES","NO") -> 0 | G11: =IF(ABS(G7*G8*G9-G10)<0.0000005,"YES","NO") -> 0 | I11: =IF(ABS(I7*I8*I9-I10)<0.0000005,"YES","NO") -> 0 | J11: =IF(ABS(J7*J8*J9-J10)<0.0000005,"YES","NO") -> 0 | K11: =IF(ABS(K7*K8*K9-K10)<0.0000005,"YES","NO") -> 0 | L11: =IF(ABS(L7*L8*L9-L10)<0.0000005,"YES","NO") -> 0 | M11: =IF(ABS(M7*M8*M9-M10)<0.0000005,"YES","NO") -> 0 | O11: =IF(ABS(O7*O8*O9-O10)<0.0000005,"YES","NO") -> 0 | P11: =IF(ABS(P7*P8*P9-P10)<0.0000005,"YES","NO") -> 0 | Q11: =IF(ABS(Q7*Q8*Q9-Q10)<0.0000005,"YES","NO") -> 0 | R11: =IF(ABS(R7*R8*R9-R10)<0.0000005,"YES","NO") -> 0 | S11: =IF(ABS(S7*S8*S9-S10)<0.0000005,"YES","NO") -> 0
A13: Modified DuPont
A14: NOPAT margin | C14: =Sources!C20/Sources!C5 -> 0 | D14: =Sources!D20/Sources!D5 -> 0 | E14: =Sources!E20/Sources!E5 -> 0 | F14: =Sources!F20/Sources!F5 -> 0 | G14: =Sources!G20/Sources!G5 -> 0 | I14: =Sources!I20/Sources!I5 -> 0 | J14: =Sources!J20/Sources!J5 -> 0 | K14: =Sources!K20/Sources!K5 -> 0 | L14: =Sources!L20/Sources!L5 -> 0 | M14: =Sources!M20/Sources!M5 -> 0 | O14: =Sources!O20/Sources!O5 -> 0 | P14: =Sources!P20/Sources!P5 -> 0 | Q14: =Sources!Q20/Sources!Q5 -> 0 | R14: =Sources!R20/Sources!R5 -> 0 | S14: =Sources!S20/Sources!S5 -> 0
A15: x Operating asset turnover (sales / avg NOA) | C15: =Sources!C5/((((Sources!B11)+(Sources!C11))/2)+(((Sources!B18)+(Sources!C18))/2)) -> 0 | D15: =Sources!D5/((((Sources!C11)+(Sources!D11))/2)+(((Sources!C18)+(Sources!D18))/2)) -> 0 | E15: =Sources!E5/((((Sources!D11)+(Sources!E11))/2)+(((Sources!D18)+(Sources!E18))/2)) -> 0 | F15: =Sources!F5/((((Sources!E11)+(Sources!F11))/2)+(((Sources!E18)+(Sources!F18))/2)) -> 0 | G15: =Sources!G5/((((Sources!F11)+(Sources!G11))/2)+(((Sources!F18)+(Sources!G18))/2)) -> 0 | I15: =Sources!I5/((((Sources!H11)+(Sources!I11))/2)+(((Sources!H18)+(Sources!I18))/2)) -> 0 | J15: =Sources!J5/((((Sources!I11)+(Sources!J11))/2)+(((Sources!I18)+(Sources!J18))/2)) -> 0 | K15: =Sources!K5/((((Sources!J11)+(Sources!K11))/2)+(((Sources!J18)+(Sources!K18))/2)) -> 0 | L15: =Sources!L5/((((Sources!K11)+(Sources!L11))/2)+(((Sources!K18)+(Sources!L18))/2)) -> 0 | M15: =Sources!M5/((((Sources!L11)+(Sources!M11))/2)+(((Sources!L18)+(Sources!M18))/2)) -> 0 | O15: =Sources!O5/((((Sources!N11)+(Sources!O11))/2)+(((Sources!N18)+(Sources!O18))/2)) -> 0 | P15: =Sources!P5/((((Sources!O11)+(Sources!P11))/2)+(((Sources!O18)+(Sources!P18))/2)) -> 0 | Q15: =Sources!Q5/((((Sources!P11)+(Sources!Q11))/2)+(((Sources!P18)+(Sources!Q18))/2)) -> 0 | R15: =Sources!R5/((((Sources!Q11)+(Sources!R11))/2)+(((Sources!Q18)+(Sources!R18))/2)) -> 0 | S15: =Sources!S5/((((Sources!R11)+(Sources!S11))/2)+(((Sources!R18)+(Sources!S18))/2)) -> 0
A16: Operating ROA | C16: =C14*C15 -> 0 | D16: =D14*D15 -> 0 | E16: =E14*E15 -> 0 | F16: =F14*F15 -> 0 | G16: =G14*G15 -> 0 | I16: =I14*I15 -> 0 | J16: =J14*J15 -> 0 | K16: =K14*K15 -> 0 | L16: =L14*L15 -> 0 | M16: =M14*M15 -> 0 | O16: =O14*O15 -> 0 | P16: =P14*P15 -> 0 | Q16: =Q14*Q15 -> 0 | R16: =R14*R15 -> 0 | S16: =S14*S15 -> 0
A17: Check: operating ROA = NOPAT margin x NOA turn | C17: =IF(ABS(C14*C15-C16)<0.0000005,"YES","NO") -> 0 | D17: =IF(ABS(D14*D15-D16)<0.0000005,"YES","NO") -> 0 | E17: =IF(ABS(E14*E15-E16)<0.0000005,"YES","NO") -> 0 | F17: =IF(ABS(F14*F15-F16)<0.0000005,"YES","NO") -> 0 | G17: =IF(ABS(G14*G15-G16)<0.0000005,"YES","NO") -> 0 | I17: =IF(ABS(I14*I15-I16)<0.0000005,"YES","NO") -> 0 | J17: =IF(ABS(J14*J15-J16)<0.0000005,"YES","NO") -> 0 | K17: =IF(ABS(K14*K15-K16)<0.0000005,"YES","NO") -> 0 | L17: =IF(ABS(L14*L15-L16)<0.0000005,"YES","NO") -> 0 | M17: =IF(ABS(M14*M15-M16)<0.0000005,"YES","NO") -> 0 | O17: =IF(ABS(O14*O15-O16)<0.0000005,"YES","NO") -> 0 | P17: =IF(ABS(P14*P15-P16)<0.0000005,"YES","NO") -> 0 | Q17: =IF(ABS(Q14*Q15-Q16)<0.0000005,"YES","NO") -> 0 | R17: =IF(ABS(R14*R15-R16)<0.0000005,"YES","NO") -> 0 | S17: =IF(ABS(S14*S15-S16)<0.0000005,"YES","NO") -> 0
A19: Operating ROA | C19: =C16 -> 0 | D19: =D16 -> 0 | E19: =E16 -> 0 | F19: =F16 -> 0 | G19: =G16 -> 0 | I19: =I16 -> 0 | J19: =J16 -> 0 | K19: =K16 -> 0 | L19: =L16 -> 0 | M19: =M16 -> 0 | O19: =O16 -> 0 | P19: =P16 -> 0 | Q19: =Q16 -> 0 | R19: =R16 -> 0 | S19: =S16 -> 0
A20: − Net interest cost (after-tax interest / avg net debt) | C20: =IF(ABS((((Sources!B18)+(Sources!C18))/2))<250,"n.m.",Sources!C19/((((Sources!B18)+(Sources!C18))/2))) -> 0 | D20: =IF(ABS((((Sources!C18)+(Sources!D18))/2))<250,"n.m.",Sources!D19/((((Sources!C18)+(Sources!D18))/2))) -> 0 | E20: =IF(ABS((((Sources!D18)+(Sources!E18))/2))<250,"n.m.",Sources!E19/((((Sources!D18)+(Sources!E18))/2))) -> 0 | F20: =IF(ABS((((Sources!E18)+(Sources!F18))/2))<250,"n.m.",Sources!F19/((((Sources!E18)+(Sources!F18))/2))) -> 0 | G20: =IF(ABS((((Sources!F18)+(Sources!G18))/2))<250,"n.m.",Sources!G19/((((Sources!F18)+(Sources!G18))/2))) -> 0 | I20: =IF(ABS((((Sources!H18)+(Sources!I18))/2))<250,"n.m.",Sources!I19/((((Sources!H18)+(Sources!I18))/2))) -> 0 | J20: =IF(ABS((((Sources!I18)+(Sources!J18))/2))<250,"n.m.",Sources!J19/((((Sources!I18)+(Sources!J18))/2))) -> 0 | K20: =IF(ABS((((Sources!J18)+(Sources!K18))/2))<250,"n.m.",Sources!K19/((((Sources!J18)+(Sources!K18))/2))) -> 0 | L20: =IF(ABS((((Sources!K18)+(Sources!L18))/2))<250,"n.m.",Sources!L19/((((Sources!K18)+(Sources!L18))/2))) -> 0 | M20: =IF(ABS((((Sources!L18)+(Sources!M18))/2))<250,"n.m.",Sources!M19/((((Sources!L18)+(Sources!M18))/2))) -> 0 | O20: =IF(ABS((((Sources!N18)+(Sources!O18))/2))<250,"n.m.",Sources!O19/((((Sources!N18)+(Sources!O18))/2))) -> 0 | P20: =IF(ABS((((Sources!O18)+(Sources!P18))/2))<250,"n.m.",Sources!P19/((((Sources!O18)+(Sources!P18))/2))) -> 0 | Q20: =IF(ABS((((Sources!P18)+(Sources!Q18))/2))<250,"n.m.",Sources!Q19/((((Sources!P18)+(Sources!Q18))/2))) -> 0 | R20: =IF(ABS((((Sources!Q18)+(Sources!R18))/2))<250,"n.m.",Sources!R19/((((Sources!Q18)+(Sources!R18))/2))) -> 0 | S20: =IF(ABS((((Sources!R18)+(Sources!S18))/2))<250,"n.m.",Sources!S19/((((Sources!R18)+(Sources!S18))/2))) -> 0
A21: Spread | C21: =IF(C20="n.m.","n.m.",C19-C20) -> 0 | D21: =IF(D20="n.m.","n.m.",D19-D20) -> 0 | E21: =IF(E20="n.m.","n.m.",E19-E20) -> 0 | F21: =IF(F20="n.m.","n.m.",F19-F20) -> 0 | G21: =IF(G20="n.m.","n.m.",G19-G20) -> 0 | I21: =IF(I20="n.m.","n.m.",I19-I20) -> 0 | J21: =IF(J20="n.m.","n.m.",J19-J20) -> 0 | K21: =IF(K20="n.m.","n.m.",K19-K20) -> 0 | L21: =IF(L20="n.m.","n.m.",L19-L20) -> 0 | M21: =IF(M20="n.m.","n.m.",M19-M20) -> 0 | O21: =IF(O20="n.m.","n.m.",O19-O20) -> 0 | P21: =IF(P20="n.m.","n.m.",P19-P20) -> 0 | Q21: =IF(Q20="n.m.","n.m.",Q19-Q20) -> 0 | R21: =IF(R20="n.m.","n.m.",R19-R20) -> 0 | S21: =IF(S20="n.m.","n.m.",S19-S20) -> 0
A22: x Net financial leverage (avg net debt / avg equity) | C22: =(((Sources!B18)+(Sources!C18))/2)/(((Sources!B11)+(Sources!C11))/2) -> 0 | D22: =(((Sources!C18)+(Sources!D18))/2)/(((Sources!C11)+(Sources!D11))/2) -> 0 | E22: =(((Sources!D18)+(Sources!E18))/2)/(((Sources!D11)+(Sources!E11))/2) -> 0 | F22: =(((Sources!E18)+(Sources!F18))/2)/(((Sources!E11)+(Sources!F11))/2) -> 0 | G22: =(((Sources!F18)+(Sources!G18))/2)/(((Sources!F11)+(Sources!G11))/2) -> 0 | I22: =(((Sources!H18)+(Sources!I18))/2)/(((Sources!H11)+(Sources!I11))/2) -> 0 | J22: =(((Sources!I18)+(Sources!J18))/2)/(((Sources!I11)+(Sources!J11))/2) -> 0 | K22: =(((Sources!J18)+(Sources!K18))/2)/(((Sources!J11)+(Sources!K11))/2) -> 0 | L22: =(((Sources!K18)+(Sources!L18))/2)/(((Sources!K11)+(Sources!L11))/2) -> 0 | M22: =(((Sources!L18)+(Sources!M18))/2)/(((Sources!L11)+(Sources!M11))/2) -> 0 | O22: =(((Sources!N18)+(Sources!O18))/2)/(((Sources!N11)+(Sources!O11))/2) -> 0 | P22: =(((Sources!O18)+(Sources!P18))/2)/(((Sources!O11)+(Sources!P11))/2) -> 0 | Q22: =(((Sources!P18)+(Sources!Q18))/2)/(((Sources!P11)+(Sources!Q11))/2) -> 0 | R22: =(((Sources!Q18)+(Sources!R18))/2)/(((Sources!Q11)+(Sources!R11))/2) -> 0 | S22: =(((Sources!R18)+(Sources!S18))/2)/(((Sources!R11)+(Sources!S11))/2) -> 0
A23: Gain or loss on financial leverage | C23: =IF(C21="n.m.","n.m.",C21*C22) -> 0 | D23: =IF(D21="n.m.","n.m.",D21*D22) -> 0 | E23: =IF(E21="n.m.","n.m.",E21*E22) -> 0 | F23: =IF(F21="n.m.","n.m.",F21*F22) -> 0 | G23: =IF(G21="n.m.","n.m.",G21*G22) -> 0 | I23: =IF(I21="n.m.","n.m.",I21*I22) -> 0 | J23: =IF(J21="n.m.","n.m.",J21*J22) -> 0 | K23: =IF(K21="n.m.","n.m.",K21*K22) -> 0 | L23: =IF(L21="n.m.","n.m.",L21*L22) -> 0 | M23: =IF(M21="n.m.","n.m.",M21*M22) -> 0 | O23: =IF(O21="n.m.","n.m.",O21*O22) -> 0 | P23: =IF(P21="n.m.","n.m.",P21*P22) -> 0 | Q23: =IF(Q21="n.m.","n.m.",Q21*Q22) -> 0 | R23: =IF(R21="n.m.","n.m.",R21*R22) -> 0 | S23: =IF(S21="n.m.","n.m.",S21*S22) -> 0
A24: ROE (NI / avg equity) | C24: =Sources!C7/(((Sources!B11)+(Sources!C11))/2) -> 0 | D24: =Sources!D7/(((Sources!C11)+(Sources!D11))/2) -> 0 | E24: =Sources!E7/(((Sources!D11)+(Sources!E11))/2) -> 0 | F24: =Sources!F7/(((Sources!E11)+(Sources!F11))/2) -> 0 | G24: =Sources!G7/(((Sources!F11)+(Sources!G11))/2) -> 0 | I24: =Sources!I7/(((Sources!H11)+(Sources!I11))/2) -> 0 | J24: =Sources!J7/(((Sources!I11)+(Sources!J11))/2) -> 0 | K24: =Sources!K7/(((Sources!J11)+(Sources!K11))/2) -> 0 | L24: =Sources!L7/(((Sources!K11)+(Sources!L11))/2) -> 0 | M24: =Sources!M7/(((Sources!L11)+(Sources!M11))/2) -> 0 | O24: =Sources!O7/(((Sources!N11)+(Sources!O11))/2) -> 0 | P24: =Sources!P7/(((Sources!O11)+(Sources!P11))/2) -> 0 | Q24: =Sources!Q7/(((Sources!P11)+(Sources!Q11))/2) -> 0 | R24: =Sources!R7/(((Sources!Q11)+(Sources!R11))/2) -> 0 | S24: =Sources!S7/(((Sources!R11)+(Sources!S11))/2) -> 0
A25: Check: ROE = operating ROA + gain | C25: =IF(C23="n.m.","n.m.",IF(ABS(C19+C23-C24)<0.0000005,"YES","NO")) -> 0 | D25: =IF(D23="n.m.","n.m.",IF(ABS(D19+D23-D24)<0.0000005,"YES","NO")) -> 0 | E25: =IF(E23="n.m.","n.m.",IF(ABS(E19+E23-E24)<0.0000005,"YES","NO")) -> 0 | F25: =IF(F23="n.m.","n.m.",IF(ABS(F19+F23-F24)<0.0000005,"YES","NO")) -> 0 | G25: =IF(G23="n.m.","n.m.",IF(ABS(G19+G23-G24)<0.0000005,"YES","NO")) -> 0 | I25: =IF(I23="n.m.","n.m.",IF(ABS(I19+I23-I24)<0.0000005,"YES","NO")) -> 0 | J25: =IF(J23="n.m.","n.m.",IF(ABS(J19+J23-J24)<0.0000005,"YES","NO")) -> 0 | K25: =IF(K23="n.m.","n.m.",IF(ABS(K19+K23-K24)<0.0000005,"YES","NO")) -> 0 | L25: =IF(L23="n.m.","n.m.",IF(ABS(L19+L23-L24)<0.0000005,"YES","NO")) -> 0 | M25: =IF(M23="n.m.","n.m.",IF(ABS(M19+M23-M24)<0.0000005,"YES","NO")) -> 0 | O25: =IF(O23="n.m.","n.m.",IF(ABS(O19+O23-O24)<0.0000005,"YES","NO")) -> 0 | P25: =IF(P23="n.m.","n.m.",IF(ABS(P19+P23-P24)<0.0000005,"YES","NO")) -> 0 | Q25: =IF(Q23="n.m.","n.m.",IF(ABS(Q19+Q23-Q24)<0.0000005,"YES","NO")) -> 0 | R25: =IF(R23="n.m.","n.m.",IF(ABS(R19+R23-R24)<0.0000005,"YES","NO")) -> 0 | S25: =IF(S23="n.m.","n.m.",IF(ABS(S19+S23-S24)<0.0000005,"YES","NO")) -> 0
A27: Operating ROA if NOPAT = operating income x 0.79 | C27: =(Sources!C6)*(1-0.21)/(((((Sources!B11)+(Sources!C11))/2)+(((Sources!B18)+(Sources!C18))/2))) -> 0 | D27: =(Sources!D6)*(1-0.21)/(((((Sources!C11)+(Sources!D11))/2)+(((Sources!C18)+(Sources!D18))/2))) -> 0 | E27: =(Sources!E6)*(1-0.21)/(((((Sources!D11)+(Sources!E11))/2)+(((Sources!D18)+(Sources!E18))/2))) -> 0 | F27: =(Sources!F6)*(1-0.21)/(((((Sources!E11)+(Sources!F11))/2)+(((Sources!E18)+(Sources!F18))/2))) -> 0 | G27: =(Sources!G6)*(1-0.21)/(((((Sources!F11)+(Sources!G11))/2)+(((Sources!F18)+(Sources!G18))/2))) -> 0 | I27: =(Sources!I6)*(1-0.21)/(((((Sources!H11)+(Sources!I11))/2)+(((Sources!H18)+(Sources!I18))/2))) -> 0 | J27: =(Sources!J6)*(1-0.21)/(((((Sources!I11)+(Sources!J11))/2)+(((Sources!I18)+(Sources!J18))/2))) -> 0 | K27: =(Sources!K6)*(1-0.21)/(((((Sources!J11)+(Sources!K11))/2)+(((Sources!J18)+(Sources!K18))/2))) -> 0 | L27: =(Sources!L6)*(1-0.21)/(((((Sources!K11)+(Sources!L11))/2)+(((Sources!K18)+(Sources!L18))/2))) -> 0 | M27: =(Sources!M6)*(1-0.21)/(((((Sources!L11)+(Sources!M11))/2)+(((Sources!L18)+(Sources!M18))/2))) -> 0 | O27: =(Sources!O6)*(1-0.21)/(((((Sources!N11)+(Sources!O11))/2)+(((Sources!N18)+(Sources!O18))/2))) -> 0 | P27: =(Sources!P6)*(1-0.21)/(((((Sources!O11)+(Sources!P11))/2)+(((Sources!O18)+(Sources!P18))/2))) -> 0 | Q27: =(Sources!Q6)*(1-0.21)/(((((Sources!P11)+(Sources!Q11))/2)+(((Sources!P18)+(Sources!Q18))/2))) -> 0 | R27: =(Sources!R6)*(1-0.21)/(((((Sources!Q11)+(Sources!R11))/2)+(((Sources!Q18)+(Sources!R18))/2))) -> 0 | S27: =(Sources!S6)*(1-0.21)/(((((Sources!R11)+(Sources!S11))/2)+(((Sources!R18)+(Sources!S18))/2))) -> 0
A29: NOPAT uses the statutory 21% federal rate on net interest only. Other income, gains, and the effective tax on operations stay inside net income, and therefore inside NOPAT. The last row taxes operating income at 21% and divides by the same average net operating assets, so the gap is the non-operating items and the tax-rate difference. Equity is the balance-sheet total. Intel's total includes non-controlling interests. Net income is consolidated net income, which for Intel is not the attributable-to-Intel line. Negative net financial leverage means net cash.
